a2a_registry/__init__.py
a2a_registry/cli.py
a2a_registry/config.py
a2a_registry/exceptions.py
a2a_registry/grpc_server.py
a2a_registry/jsonrpc_server.py
a2a_registry/server.py
a2a_registry/storage.py
a2a_registry/vector_enhanced_storage.py
a2a_registry/vector_generator.py
a2a_registry/vector_store.py
a2a_registry/graphql/__init__.py
a2a_registry/graphql/app.py
a2a_registry/graphql/dataloaders.py
a2a_registry/graphql/pagination.py
a2a_registry/graphql/resolvers.py
a2a_registry/graphql/schema.py
a2a_registry/graphql/security.py
a2a_registry/graphql/services.py
a2a_registry/graphql/storage.py
a2a_registry/graphql/types.py
a2a_registry/proto/__init__.py
a2a_registry/proto/generated/__init__.py
a2a_registry/proto/generated/a2a_pb2.py
a2a_registry/proto/generated/a2a_pb2_grpc.py
a2a_registry/proto/generated/registry_pb2.py
a2a_registry/proto/generated/registry_pb2_grpc.py
a2a_registry-0.1.5.dist-info/METADATA
a2a_registry-0.1.5.dist-info/WHEEL
a2a_registry-0.1.5.dist-info/entry_points.txt
a2a_registry-0.1.5.dist-info/top_level.txt
a2a_registry-0.1.5.dist-info/RECORD
