Metadata-Version: 2.4
Name: a2a-registry
Version: 0.1.5
Summary: A2A Registry - Protocol buffer definitions and Python client for A2A message registry
Author-email: Allen Day <allenday@users.github.com>
License: MIT
Project-URL: Homepage, https://github.com/allenday/a2a-registry
Project-URL: Repository, https://github.com/allenday/a2a-registry
Project-URL: Issues, https://github.com/allenday/a2a-registry/issues
Classifier: Development Status :: 4 - Beta
Classifier: Intended Audience :: Developers
Classifier: Programming Language :: Python :: 3
Classifier: Programming Language :: Python :: 3.11
Classifier: Programming Language :: Python :: 3.12
Classifier: Programming Language :: Python :: 3.13
Requires-Python: >=3.11
Requires-Dist: fastapi>=0.95.0
Requires-Dist: httpx>=0.28.1
Requires-Dist: httpx-sse>=0.4.0
Requires-Dist: pydantic>=2.11.3
Requires-Dist: sse-starlette
Requires-Dist: starlette
Requires-Dist: protobuf>=5.29.5
Requires-Dist: google-api-core>=1.26.0
Requires-Dist: grpcio>=1.60
Requires-Dist: grpcio-tools>=1.60
Requires-Dist: grpcio_reflection>=1.7.0
Requires-Dist: fasta2a
Requires-Dist: uvicorn>=0.20.0
Requires-Dist: click>=8.0.0
Requires-Dist: jsonrpcserver>=5.0.0
Requires-Dist: strawberry-graphql[fastapi]>=0.234.0
Requires-Dist: pyjwt>=2.8.0
Requires-Dist: redis>=5.0.0
Requires-Dist: sentence-transformers>=2.2.0
Requires-Dist: numpy>=1.21.0
Requires-Dist: faiss-cpu>=1.7.0
Provides-Extra: dev
Requires-Dist: black>=23.0.0; extra == "dev"
Requires-Dist: ruff>=0.1.0; extra == "dev"
Requires-Dist: mypy>=1.0.0; extra == "dev"
Requires-Dist: mypy-protobuf>=3.4.0; extra == "dev"
Requires-Dist: types-grpcio>=1.0.0; extra == "dev"
Requires-Dist: pytest>=7.0.0; extra == "dev"
Requires-Dist: pytest-asyncio>=0.21.0; extra == "dev"
Requires-Dist: pytest-cov>=4.0.0; extra == "dev"
Requires-Dist: build>=0.10.0; extra == "dev"
Requires-Dist: twine>=4.0.0; extra == "dev"
Requires-Dist: pre-commit>=3.0.0; extra == "dev"
Provides-Extra: docs
Requires-Dist: mkdocs>=1.5.0; extra == "docs"
Requires-Dist: mkdocs-material>=9.4.0; extra == "docs"
Requires-Dist: mkdocstrings[python]>=0.24.0; extra == "docs"
Requires-Dist: mkdocs-gen-files>=0.5.0; extra == "docs"
Requires-Dist: mkdocs-literate-nav>=0.6.0; extra == "docs"
Requires-Dist: mkdocs-section-index>=0.3.0; extra == "docs"
Requires-Dist: mkdocs-autorefs>=0.5.0; extra == "docs"
